pyOKAERTool/__init__.py
pyOKAERTool/_ok.pyd
pyOKAERTool/_ok.so
pyOKAERTool/main.py
pyOKAERTool/ok-5.3.6-py3-none-any.whl
pyOKAERTool/ok.py
pyOKAERTool/okFrontPanel.dll
pyokaertool-0.2.6.dist-info/METADATA
pyokaertool-0.2.6.dist-info/WHEEL
pyokaertool-0.2.6.dist-info/top_level.txt
pyokaertool-0.2.6.dist-info/RECORD
