Metadata-Version: 2.4
Name: pyokaertool
Version: 0.2.6
Summary: A Python package for AER Tool functionalities on a OpalKelly FPGA platform.
Author: Antonio Ríos-Navarro
Author-email: arios@us.es
Requires-Dist: numpy>=2.2.2
Dynamic: author
Dynamic: author-email
Dynamic: requires-dist
Dynamic: summary
